{
  "string": [
    {
      "name": "module_desc",
      "value": "模块描述"
    },
    {
      "name": "EntryAbility_desc",
      "value": "description"
    },
    {
      "name": "EntryAbility_label",
      "value": "读书"
    },
    {
      "name": "bottom_text_read",
      "value": "阅读"
    },
    {
      "name": "bottom_text_book",
      "value": "书架"
    },
    {
      "name": "bottom_text_voice",
      "value": "读书"
    },
    {
      "name": "bottom_text_me",
      "value": "我的"
    },
    {
      "name": "setting_list_account",
      "value": "我的账户"
    },
    {
      "name": "setting_list_record",
      "value": "读书记录"
    },
    {
      "name": "setting_list_setting",
      "value": "设置"
    }
  ]
}